datasette_examples/__init__.py
datasette_examples-0.1a0.dist-info/LICENSE
datasette_examples-0.1a0.dist-info/METADATA
datasette_examples-0.1a0.dist-info/WHEEL
datasette_examples-0.1a0.dist-info/entry_points.txt
datasette_examples-0.1a0.dist-info/top_level.txt
datasette_examples-0.1a0.dist-info/RECORD
