Metadata-Version: 2.1
Name: datasette-examples
Version: 0.1a0
Summary: Load example SQL scripts into Datasette on startup
Author: Simon Willison
License: Apache-2.0
Project-URL: Homepage, https://github.com/datasette/datasette-examples
Project-URL: Changelog, https://github.com/datasette/datasette-examples/releases
Project-URL: Issues, https://github.com/datasette/datasette-examples/issues
Project-URL: CI, https://github.com/datasette/datasette-examples/actions
Classifier: Framework :: Datasette
Classifier: License :: OSI Approved :: Apache Software License
Requires-Python: >=3.8
License-File: LICENSE
Requires-Dist: datasette
Provides-Extra: test
Requires-Dist: pytest ; extra == 'test'
Requires-Dist: pytest-asyncio ; extra == 'test'
Requires-Dist: pytest-httpx ; extra == 'test'
